proxyscraper/__init__.py
proxyscraper/proxy.py
proxyscraper-0.0.1.dist-info/METADATA
proxyscraper-0.0.1.dist-info/RECORD
proxyscraper-0.0.1.dist-info/WHEEL
proxyscraper-0.0.1.dist-info/top_level.txt
