Metadata-Version: 2.1
Name: proxyscraper
Version: 0.0.1
Summary: Scrape proxy details from popular web pages
Home-page: https://github.com/okinskas/proxyscraper
Author: Ovidijus Okinskas
Author-email: ovidijus.okinskas@gmail.com
License: UNKNOWN
Platform: UNKNOWN
Classifier: Programming Language :: Python :: 3
Classifier: License :: OSI Approved :: MIT License
Classifier: Operating System :: OS Independent
